AriEngine/__init__.py
AriEngine-1.1.dist-info/LICENSE
AriEngine-1.1.dist-info/METADATA
AriEngine-1.1.dist-info/WHEEL
AriEngine-1.1.dist-info/top_level.txt
AriEngine-1.1.dist-info/RECORD
