Metadata-Version: 2.1
Name: AriEngine
Version: 1.1
Summary: this is still in progress
Home-page: UNKNOWN
Author: AriDombe
Author-email: copuwu@gmail.com
License: UNKNOWN
Platform: UNKNOWN
Classifier: Programming Language :: Python :: 3
Classifier: License :: OSI Approved :: MIT License
Classifier: Operating System :: OS Independent
Requires-Python: >=3.6
